{
  "version": "g5-life-pack2plus-samples-v1",
  "module": "life_pack2plus",
  "topic": "小五生活應用題｜第二包 基礎入門｜帝國",
  "note": "每單元前 5 題示例，共 10 單元 50 題",
  "questions": [
    {
      "id": "g5lp2p_u1_avg_001",
      "kind": "u1_average",
      "topic": "小五生活應用題｜第二包 基礎入門｜帝國",
      "difficulty": "easy",
      "question": "有 24 顆糖平均分給 6 位同學，每位同學分到幾顆？",
      "answer": "4",
      "answer_mode": "number",
      "hints": ["先判斷：平均分配通常用除法。", "列式：總量 ÷ 人數。", "先算 24 ÷ 6，再檢查單位是『每位同學』。"],
      "steps": ["平均分配=除法", "24 ÷ 6", "寫出每位同學分到的顆數"],
      "explanation": "24 ÷ 6 = 4。",
      "common_mistakes": ["把平均分配寫成乘法", "答案未對應每位"],
      "tags": ["生活應用", "平均分配"],
      "core": ["平均分配", "除法"],
      "meta": {"unit": "u1"}
    },
    {
      "id": "g5lp2p_u1_avg_002",
      "kind": "u1_average",
      "topic": "小五生活應用題｜第二包 基礎入門｜帝國",
      "difficulty": "medium",
      "question": "有 3/4 公升果汁平均分給 3 人，每人分到幾公升？（最簡分數）",
      "answer": "1/4",
      "answer_mode": "fraction",
      "hints": ["分數平均分配一樣是除法。", "列式：3/4 ÷ 3。", "把除以 3 改成乘以 1/3，再約分。"],
      "steps": ["列式 3/4 ÷ 3", "改寫為 3/4 × 1/3", "約分得最簡分數"],
      "explanation": "3/4 ÷ 3 = 3/12 = 1/4。",
      "common_mistakes": ["把 ÷3 寫成 ×3", "忘記約分"],
      "tags": ["生活應用", "平均分配", "分數"],
      "core": ["分數除法", "平均分配"],
      "meta": {"unit": "u1"}
    },
    {
      "id": "g5lp2p_u1_avg_003",
      "kind": "u1_average",
      "topic": "小五生活應用題｜第二包 基礎入門｜帝國",
      "difficulty": "easy",
      "question": "45 公尺緞帶平均分給 9 組，每組幾公尺？",
      "answer": "5",
      "answer_mode": "number",
      "hints": ["抓關鍵字：平均分給。", "列式：45 ÷ 9。", "算完後確認單位是公尺/組。"],
      "steps": ["平均分配", "45 ÷ 9", "寫上單位"],
      "explanation": "45 ÷ 9 = 5。",
      "common_mistakes": ["漏寫單位", "把 45 和 9 顛倒"],
      "tags": ["生活應用", "平均分配"],
      "core": ["整數除法"],
      "meta": {"unit": "u1"}
    },
    {
      "id": "g5lp2p_u1_avg_004",
      "kind": "u1_average",
      "topic": "小五生活應用題｜第二包 基礎入門｜帝國",
      "difficulty": "hard",
      "question": "有 5/2 公斤米平均分給 5 人，每人幾公斤？（最簡分數）",
      "answer": "1/2",
      "answer_mode": "fraction",
      "hints": ["先判斷：分數平均分配。", "列式：5/2 ÷ 5。", "改寫乘倒數後先約分再計算。"],
      "steps": ["5/2 ÷ 5", "5/2 × 1/5", "約分得 1/2"],
      "explanation": "5/2 ÷ 5 = 5/10 = 1/2。",
      "common_mistakes": ["不會改乘倒數", "沒有做約分"],
      "tags": ["生活應用", "分數"],
      "core": ["分數除法"],
      "meta": {"unit": "u1"}
    },
    {
      "id": "g5lp2p_u1_avg_005",
      "kind": "u1_average",
      "topic": "小五生活應用題｜第二包 基礎入門｜帝國",
      "difficulty": "medium",
      "question": "18 本書平均放進 3 個箱子，每箱幾本？",
      "answer": "6",
      "answer_mode": "number",
      "hints": ["這題是平均分配。", "列式：18 ÷ 3。", "檢查：每箱本數 × 箱數要回到總本數。"],
      "steps": ["18 ÷ 3", "得到每箱本數", "回代檢查"],
      "explanation": "18 ÷ 3 = 6。",
      "common_mistakes": ["忘記回代檢查", "把總數再加一次"],
      "tags": ["生活應用", "平均分配"],
      "core": ["除法"],
      "meta": {"unit": "u1"}
    },

    {
      "id": "g5lp2p_u2_frac_001",
      "kind": "u2_fraction_add_sub",
      "topic": "小五生活應用題｜第二包 基礎入門｜帝國",
      "difficulty": "easy",
      "question": "小明喝了 1/3 瓶牛奶，小華又喝了 1/6 瓶，一共喝了幾瓶？（最簡分數）",
      "answer": "1/2",
      "answer_mode": "fraction",
      "hints": ["先看分母是否相同。", "分母不同先通分。", "通分後再加分子並約分。"],
      "steps": ["1/3 與 1/6 通分", "2/6 + 1/6", "得 3/6 = 1/2"],
      "explanation": "1/3 + 1/6 = 2/6 + 1/6 = 3/6 = 1/2。",
      "common_mistakes": ["分母直接相加", "忘記約分"],
      "tags": ["生活應用", "分數加法"],
      "core": ["通分", "約分"],
      "meta": {"unit": "u2"}
    },
    {
      "id": "g5lp2p_u2_frac_002",
      "kind": "u2_fraction_add_sub",
      "topic": "小五生活應用題｜第二包 基礎入門｜帝國",
      "difficulty": "easy",
      "question": "一條繩子長 5/8 公尺，剪掉 1/4 公尺，還剩多少公尺？（最簡分數）",
      "answer": "3/8",
      "answer_mode": "fraction",
      "hints": ["這是分數減法。", "先把 1/4 通分成八分母。", "再做分子相減。"],
      "steps": ["1/4 = 2/8", "5/8 - 2/8", "得 3/8"],
      "explanation": "5/8 - 1/4 = 5/8 - 2/8 = 3/8。",
      "common_mistakes": ["1/4 直接減分母", "借位觀念混淆"],
      "tags": ["生活應用", "分數減法"],
      "core": ["同分母減法"],
      "meta": {"unit": "u2"}
    },
    {
      "id": "g5lp2p_u2_frac_003",
      "kind": "u2_fraction_add_sub",
      "topic": "小五生活應用題｜第二包 基礎入門｜帝國",
      "difficulty": "medium",
      "question": "菜園上午澆了 2/5 區，下午又澆了 3/10 區，一共澆了幾區？（最簡分數）",
      "answer": "7/10",
      "answer_mode": "fraction",
      "hints": ["先找最小公分母。", "2/5 先改寫成十分母。", "再把兩個分數相加。"],
      "steps": ["2/5 = 4/10", "4/10 + 3/10", "得 7/10"],
      "explanation": "2/5 + 3/10 = 4/10 + 3/10 = 7/10。",
      "common_mistakes": ["通分錯", "算完沒檢查是否最簡"],
      "tags": ["生活應用", "分數加法"],
      "core": ["通分"],
      "meta": {"unit": "u2"}
    },
    {
      "id": "g5lp2p_u2_frac_004",
      "kind": "u2_fraction_add_sub",
      "topic": "小五生活應用題｜第二包 基礎入門｜帝國",
      "difficulty": "hard",
      "question": "蛋糕吃掉了 7/9，還要再吃掉 2/3 才算全部吃完嗎？目前還剩多少？（最簡分數）",
      "answer": "2/9",
      "answer_mode": "fraction",
      "hints": ["先算剩下多少：1 - 已吃。", "1 可寫成 9/9。", "再做分數減法。"],
      "steps": ["1 = 9/9", "9/9 - 7/9", "得 2/9"],
      "explanation": "剩下 1 - 7/9 = 2/9。",
      "common_mistakes": ["把 2/3 當作本題必要計算", "1 沒轉成同分母"],
      "tags": ["生活應用", "剩餘量"],
      "core": ["全體-部分"],
      "meta": {"unit": "u2"}
    },
    {
      "id": "g5lp2p_u2_frac_005",
      "kind": "u2_fraction_add_sub",
      "topic": "小五生活應用題｜第二包 基礎入門｜帝國",
      "difficulty": "hard",
      "question": "一段路上午走了 1又1/4 公里，下午走了 2/3 公里，共走多少公里？（最簡分數）",
      "answer": "23/12",
      "answer_mode": "fraction",
      "hints": ["帶分數先換成假分數。", "再與 2/3 通分相加。", "最後可檢查是否要寫成帶分數。"],
      "steps": ["1又1/4 = 5/4", "5/4 + 2/3", "得 15/12 + 8/12 = 23/12"],
      "explanation": "1又1/4 + 2/3 = 5/4 + 2/3 = 23/12。",
      "common_mistakes": ["帶分數未轉假分數", "通分錯"],
      "tags": ["生活應用", "帶分數"],
      "core": ["假分數", "通分"],
      "meta": {"unit": "u2"}
    },

    {
      "id": "g5lp2p_u3_money_001",
      "kind": "u3_money",
      "topic": "小五生活應用題｜第二包 基礎入門｜帝國",
      "difficulty": "easy",
      "question": "每枝筆 35 元，買 3 枝要多少元？",
      "answer": "105",
      "answer_mode": "number",
      "hints": ["這題是單價×數量。", "列式：35 × 3。", "算後確認單位是元。"],
      "steps": ["單價×數量", "35×3", "寫出總價"],
      "explanation": "35 × 3 = 105 元。",
      "common_mistakes": ["把乘法寫成加法一次", "漏單位"],
      "tags": ["生活應用", "金額"],
      "core": ["總價"],
      "meta": {"unit": "u3"}
    },
    {
      "id": "g5lp2p_u3_money_002",
      "kind": "u3_money",
      "topic": "小五生活應用題｜第二包 基礎入門｜帝國",
      "difficulty": "easy",
      "question": "小美有 200 元，買了 128 元的文具，還剩多少元？",
      "answer": "72",
      "answer_mode": "number",
      "hints": ["先求找零：付款 - 消費。", "列式：200 - 128。", "檢查剩下的金額應小於 200。"],
      "steps": ["付款-消費", "200-128", "得到找零"],
      "explanation": "200 - 128 = 72 元。",
      "common_mistakes": ["把減法方向寫反", "粗心借位錯"],
      "tags": ["生活應用", "找零"],
      "core": ["金額減法"],
      "meta": {"unit": "u3"}
    },
    {
      "id": "g5lp2p_u3_money_003",
      "kind": "u3_money",
      "topic": "小五生活應用題｜第二包 基礎入門｜帝國",
      "difficulty": "medium",
      "question": "便當 48 元買 4 個，另加飲料 35 元，總共多少元？",
      "answer": "227",
      "answer_mode": "number",
      "hints": ["先算便當總價，再加飲料。", "列式：(48×4)+35。", "檢查是否為兩段加總。"],
      "steps": ["48×4", "把結果+35", "寫出總金額"],
      "explanation": "48×4=192，192+35=227。",
      "common_mistakes": ["先加後乘", "漏算其中一項"],
      "tags": ["生活應用", "多步驟金額"],
      "core": ["先乘後加"],
      "meta": {"unit": "u3"}
    },
    {
      "id": "g5lp2p_u3_money_004",
      "kind": "u3_money",
      "topic": "小五生活應用題｜第二包 基礎入門｜帝國",
      "difficulty": "hard",
      "question": "每盒點心 129 元，買 3 盒付 500 元，應找回多少元？",
      "answer": "113",
      "answer_mode": "number",
      "hints": ["先求總價：單價×數量。", "再做找零：付款-總價。", "兩步驟都要檢查金額合理。"],
      "steps": ["129×3", "500-總價", "得到找零"],
      "explanation": "129×3=387，500-387=113。",
      "common_mistakes": ["付款減單價一次", "乘法計算錯"],
      "tags": ["生活應用", "找零"],
      "core": ["總價與找零"],
      "meta": {"unit": "u3"}
    },
    {
      "id": "g5lp2p_u3_money_005",
      "kind": "u3_money",
      "topic": "小五生活應用題｜第二包 基礎入門｜帝國",
      "difficulty": "medium",
      "question": "一包餅乾 360 元，共 8 小包，每小包平均幾元？",
      "answer": "45",
      "answer_mode": "number",
      "hints": ["平均單價：總價 ÷ 份數。", "列式：360 ÷ 8。", "檢查 45×8 是否回到 360。"],
      "steps": ["360÷8", "得到每包價", "回代檢查"],
      "explanation": "360 ÷ 8 = 45。",
      "common_mistakes": ["把 360 與 8 顛倒", "不做回代檢查"],
      "tags": ["生活應用", "平均單價"],
      "core": ["除法", "單價"],
      "meta": {"unit": "u3"}
    },

    {
      "id": "g5lp2p_u4_pct_001",
      "kind": "u4_discount_percent",
      "topic": "小五生活應用題｜第二包 基礎入門｜帝國",
      "difficulty": "easy",
      "question": "一件外套原價 250 元，打 8 折後是多少元？",
      "answer": "200",
      "answer_mode": "number",
      "hints": ["8 折就是付 80%。", "列式：原價×0.8。", "先算折後價，再檢查比原價小。"],
      "steps": ["8折=0.8", "250×0.8", "得折後價"],
      "explanation": "250×0.8=200。",
      "common_mistakes": ["把 8 折當減 8 元", "80% 轉小數錯"],
      "tags": ["生活應用", "折扣"],
      "core": ["百分率", "小數"],
      "meta": {"unit": "u4"}
    },
    {
      "id": "g5lp2p_u4_pct_002",
      "kind": "u4_discount_percent",
      "topic": "小五生活應用題｜第二包 基礎入門｜帝國",
      "difficulty": "easy",
      "question": "原價 400 元，打 75 折後多少元？",
      "answer": "300",
      "answer_mode": "number",
      "hints": ["75 折=75%=0.75。", "列式：400×0.75。", "折後價應小於原價。"],
      "steps": ["0.75", "400×0.75", "得 300"],
      "explanation": "400×0.75=300。",
      "common_mistakes": ["把 75 折算成 400-75", "小數位錯"],
      "tags": ["生活應用", "折扣"],
      "core": ["百分率"],
      "meta": {"unit": "u4"}
    },
    {
      "id": "g5lp2p_u4_pct_003",
      "kind": "u4_discount_percent",
      "topic": "小五生活應用題｜第二包 基礎入門｜帝國",
      "difficulty": "medium",
      "question": "原價 560 元，打 85 折，折扣了多少元？",
      "answer": "84",
      "answer_mode": "number",
      "hints": ["折扣額 = 原價×(1-折扣率)。", "85 折表示折扣率是 15%。", "先算折扣額，不要先當折後價。"],
      "steps": ["1-0.85=0.15", "560×0.15", "得折扣額"],
      "explanation": "560×0.15=84。",
      "common_mistakes": ["把 85% 當折扣額", "折後價與折扣額混淆"],
      "tags": ["生活應用", "折扣額"],
      "core": ["百分率"],
      "meta": {"unit": "u4"}
    },
    {
      "id": "g5lp2p_u4_pct_004",
      "kind": "u4_discount_percent",
      "topic": "小五生活應用題｜第二包 基礎入門｜帝國",
      "difficulty": "hard",
      "question": "某商品打 8 折後是 320 元，原價是多少元？",
      "answer": "400",
      "answer_mode": "number",
      "hints": ["這是回推原價。", "折後=原價×0.8。", "原價=折後÷0.8。"],
      "steps": ["列式 320=原價×0.8", "原價=320÷0.8", "得 400"],
      "explanation": "320÷0.8=400。",
      "common_mistakes": ["把 320 再乘 0.8", "不會做回推"],
      "tags": ["生活應用", "回推"],
      "core": ["乘除互逆"],
      "meta": {"unit": "u4"}
    },
    {
      "id": "g5lp2p_u4_pct_005",
      "kind": "u4_discount_percent",
      "topic": "小五生活應用題｜第二包 基礎入門｜帝國",
      "difficulty": "medium",
      "question": "同價商品甲店 9 折、乙店 85 折，哪一家較便宜？",
      "answer": "乙店",
      "answer_mode": "text",
      "hints": ["折數越小，折後價格越低。", "9 折=90%，85 折=85%。", "比較付出的百分率大小。"],
      "steps": ["9折=90%", "85折=85%", "85%較低所以較便宜"],
      "explanation": "同原價下，85% 的價格低於 90%，乙店較便宜。",
      "common_mistakes": ["把折數大誤認為折更多", "未轉成百分率比較"],
      "tags": ["生活應用", "折扣比較"],
      "core": ["百分率比較"],
      "meta": {"unit": "u4"}
    },

    {
      "id": "g5lp2p_u5_ratio_001",
      "kind": "u5_ratio_proportion",
      "topic": "小五生活應用題｜第二包 基礎入門｜帝國",
      "difficulty": "easy",
      "question": "果汁配方果汁:水 = 2:3，若果汁用 6 杯，水要幾杯？",
      "answer": "9",
      "answer_mode": "number",
      "hints": ["先找倍率：2 到 6 放大幾倍。", "兩邊要同倍放大。", "水的 3 也乘同倍率。"],
      "steps": ["倍率=6÷2=3", "水=3×3", "得 9"],
      "explanation": "同倍放大 3 倍，水為 9 杯。",
      "common_mistakes": ["只放大一邊", "比值順序顛倒"],
      "tags": ["生活應用", "比例"],
      "core": ["等比"],
      "meta": {"unit": "u5"}
    },
    {
      "id": "g5lp2p_u5_ratio_002",
      "kind": "u5_ratio_proportion",
      "topic": "小五生活應用題｜第二包 基礎入門｜帝國",
      "difficulty": "medium",
      "question": "4 顆蘋果 52 元，10 顆蘋果多少元？（假設單價固定）",
      "answer": "130",
      "answer_mode": "number",
      "hints": ["先求每顆單價。", "再乘要買的顆數。", "可用比例表檢查。"],
      "steps": ["52÷4=13", "13×10", "得 130"],
      "explanation": "單價 13 元，10 顆共 130 元。",
      "common_mistakes": ["52 直接乘 10", "忘記先求單位率"],
      "tags": ["生活應用", "單位率"],
      "core": ["比例", "單價"],
      "meta": {"unit": "u5"}
    },
    {
      "id": "g5lp2p_u5_ratio_003",
      "kind": "u5_ratio_proportion",
      "topic": "小五生活應用題｜第二包 基礎入門｜帝國",
      "difficulty": "hard",
      "question": "地圖比例尺 1:50000，地圖上 3 公分，實際距離多少公里？",
      "answer": "1.5",
      "answer_mode": "number",
      "hints": ["先用比例尺求實際公分。", "再把公分換成公里。", "注意 100000 公分 = 1 公里。"],
      "steps": ["3×50000=150000 公分", "150000÷100000", "得 1.5 公里"],
      "explanation": "實際距離 150000 公分 = 1.5 公里。",
      "common_mistakes": ["比例尺方向搞反", "單位換算錯"],
      "tags": ["生活應用", "比例尺"],
      "core": ["比例", "單位換算"],
      "meta": {"unit": "u5"}
    },
    {
      "id": "g5lp2p_u5_ratio_004",
      "kind": "u5_ratio_proportion",
      "topic": "小五生活應用題｜第二包 基礎入門｜帝國",
      "difficulty": "medium",
      "question": "男生:女生 = 3:5，全班 40 人，女生幾人？",
      "answer": "25",
      "answer_mode": "number",
      "hints": ["先算總份數。", "每份 = 總人數 ÷ 總份數。", "女生份數乘每份。"],
      "steps": ["總份=3+5=8", "每份=40÷8=5", "女生=5×5=25"],
      "explanation": "女生 25 人。",
      "common_mistakes": ["把 3:5 直接當 3+5 人", "總份數算錯"],
      "tags": ["生活應用", "比"],
      "core": ["份量法"],
      "meta": {"unit": "u5"}
    },
    {
      "id": "g5lp2p_u5_ratio_005",
      "kind": "u5_ratio_proportion",
      "topic": "小五生活應用題｜第二包 基礎入門｜帝國",
      "difficulty": "hard",
      "question": "紅:白顏料=2:1，總共 18 杯，紅色要幾杯？",
      "answer": "12",
      "answer_mode": "number",
      "hints": ["先算總份數 2+1。", "每份 = 18 ÷ 總份。", "紅色是 2 份。"],
      "steps": ["總份=3", "每份=6", "紅色=2×6=12"],
      "explanation": "紅色 12 杯。",
      "common_mistakes": ["總份數忘記相加", "求到每份就停"],
      "tags": ["生活應用", "比例配方"],
      "core": ["份量比"],
      "meta": {"unit": "u5"}
    },

    {
      "id": "g5lp2p_u6_unit_001",
      "kind": "u6_unit_decimal",
      "topic": "小五生活應用題｜第二包 基礎入門｜帝國",
      "difficulty": "easy",
      "question": "3.5 公斤等於多少公克？",
      "answer": "3500",
      "answer_mode": "number",
      "hints": ["公斤轉公克要乘 1000。", "列式：3.5×1000。", "注意小數點位移。"],
      "steps": ["1kg=1000g", "3.5×1000", "得 3500g"],
      "explanation": "3.5 公斤 = 3500 公克。",
      "common_mistakes": ["誤除以 1000", "小數點方向錯"],
      "tags": ["生活應用", "單位換算"],
      "core": ["公斤公克"],
      "meta": {"unit": "u6"}
    },
    {
      "id": "g5lp2p_u6_unit_002",
      "kind": "u6_unit_decimal",
      "topic": "小五生活應用題｜第二包 基礎入門｜帝國",
      "difficulty": "medium",
      "question": "2 公尺 35 公分等於幾公尺？",
      "answer": "2.35",
      "answer_mode": "number",
      "hints": ["先把公分換成公尺。", "35 公分 = 0.35 公尺。", "再和 2 公尺相加。"],
      "steps": ["35cm=0.35m", "2+0.35", "得 2.35m"],
      "explanation": "2 公尺 35 公分 = 2.35 公尺。",
      "common_mistakes": ["35 公分誤寫 0.035", "未先同單位"],
      "tags": ["生活應用", "長度換算"],
      "core": ["公尺公分"],
      "meta": {"unit": "u6"}
    },
    {
      "id": "g5lp2p_u6_unit_003",
      "kind": "u6_unit_decimal",
      "topic": "小五生活應用題｜第二包 基礎入門｜帝國",
      "difficulty": "easy",
      "question": "1.2 公升等於多少毫升？",
      "answer": "1200",
      "answer_mode": "number",
      "hints": ["公升轉毫升乘 1000。", "列式：1.2×1000。", "檢查答案應大於 1.2。"],
      "steps": ["1L=1000mL", "1.2×1000", "得 1200mL"],
      "explanation": "1.2 公升 = 1200 毫升。",
      "common_mistakes": ["誤除 1000", "單位抄錯"],
      "tags": ["生活應用", "容量換算"],
      "core": ["公升毫升"],
      "meta": {"unit": "u6"}
    },
    {
      "id": "g5lp2p_u6_unit_004",
      "kind": "u6_unit_decimal",
      "topic": "小五生活應用題｜第二包 基礎入門｜帝國",
      "difficulty": "medium",
      "question": "4500 公尺等於幾公里？",
      "answer": "4.5",
      "answer_mode": "number",
      "hints": ["公尺轉公里除 1000。", "列式：4500÷1000。", "檢查公里值應小於公尺值。"],
      "steps": ["1km=1000m", "4500÷1000", "得 4.5km"],
      "explanation": "4500 公尺 = 4.5 公里。",
      "common_mistakes": ["誤乘 1000", "小數點錯位"],
      "tags": ["生活應用", "長度換算"],
      "core": ["公尺公里"],
      "meta": {"unit": "u6"}
    },
    {
      "id": "g5lp2p_u6_unit_005",
      "kind": "u6_unit_decimal",
      "topic": "小五生活應用題｜第二包 基礎入門｜帝國",
      "difficulty": "hard",
      "question": "0.75 公斤加 250 公克，共幾公斤？",
      "answer": "1",
      "answer_mode": "number",
      "hints": ["先統一成同單位。", "250 公克可換成 0.25 公斤。", "再做加法。"],
      "steps": ["250g=0.25kg", "0.75+0.25", "得 1kg"],
      "explanation": "共 1 公斤。",
      "common_mistakes": ["直接 0.75+250", "單位未統一"],
      "tags": ["生活應用", "單位換算"],
      "core": ["重量換算"],
      "meta": {"unit": "u6"}
    },

    {
      "id": "g5lp2p_u7_speed_001",
      "kind": "u7_speed",
      "topic": "小五生活應用題｜第二包 基礎入門｜帝國",
      "difficulty": "easy",
      "question": "汽車 2 小時行駛 120 公里，平均每小時幾公里？",
      "answer": "60",
      "answer_mode": "number",
      "hints": ["先辨識要找速率。", "速率=路程÷時間。", "把 120 ÷ 2 算出來。"],
      "steps": ["公式", "120÷2", "得 60 km/h"],
      "explanation": "速率 = 120÷2 = 60 公里/小時。",
      "common_mistakes": ["公式倒置", "單位漏寫"],
      "tags": ["生活應用", "速率"],
      "core": ["速率公式"],
      "meta": {"unit": "u7"}
    },
    {
      "id": "g5lp2p_u7_speed_002",
      "kind": "u7_speed",
      "topic": "小五生活應用題｜第二包 基礎入門｜帝國",
      "difficulty": "easy",
      "question": "一列車每小時 45 公里，行駛 3 小時，共行駛幾公里？",
      "answer": "135",
      "answer_mode": "number",
      "hints": ["這題要找路程。", "路程=速率×時間。", "列式 45×3。"],
      "steps": ["公式", "45×3", "得 135 公里"],
      "explanation": "路程 = 45×3 = 135 公里。",
      "common_mistakes": ["把乘法寫成除法", "單位混淆"],
      "tags": ["生活應用", "速率"],
      "core": ["路程公式"],
      "meta": {"unit": "u7"}
    },
    {
      "id": "g5lp2p_u7_speed_003",
      "kind": "u7_speed",
      "topic": "小五生活應用題｜第二包 基礎入門｜帝國",
      "difficulty": "medium",
      "question": "若速率 50 公里/小時，走完 150 公里需要幾小時？",
      "answer": "3",
      "answer_mode": "number",
      "hints": ["這題求時間。", "時間=路程÷速率。", "列式 150÷50。"],
      "steps": ["公式", "150÷50", "得 3 小時"],
      "explanation": "時間 = 150÷50 = 3 小時。",
      "common_mistakes": ["公式方向錯", "小時單位漏掉"],
      "tags": ["生活應用", "速率"],
      "core": ["時間公式"],
      "meta": {"unit": "u7"}
    },
    {
      "id": "g5lp2p_u7_speed_004",
      "kind": "u7_speed",
      "topic": "小五生活應用題｜第二包 基礎入門｜帝國",
      "difficulty": "medium",
      "question": "800 公尺跑了 4 分鐘，平均每分鐘跑幾公尺？",
      "answer": "200",
      "answer_mode": "number",
      "hints": ["單位已一致（公尺、分鐘）。", "速率=路程÷時間。", "列式 800÷4。"],
      "steps": ["800÷4", "得 200", "單位是 m/min"],
      "explanation": "平均每分鐘 200 公尺。",
      "common_mistakes": ["把分鐘當小時", "忘記寫每分鐘"],
      "tags": ["生活應用", "速率"],
      "core": ["單位率"],
      "meta": {"unit": "u7"}
    },
    {
      "id": "g5lp2p_u7_speed_005",
      "kind": "u7_speed",
      "topic": "小五生活應用題｜第二包 基礎入門｜帝國",
      "difficulty": "hard",
      "question": "72 公里花 90 分鐘，平均速率是每小時幾公里？",
      "answer": "48",
      "answer_mode": "number",
      "hints": ["先把 90 分鐘換成小時。", "90 分鐘 = 1.5 小時。", "速率=72÷1.5。"],
      "steps": ["90分=1.5小時", "72÷1.5", "得 48 km/h"],
      "explanation": "平均速率 48 公里/小時。",
      "common_mistakes": ["分鐘未換小時", "72÷90 直接當答案"],
      "tags": ["生活應用", "速率", "時間換算"],
      "core": ["單位一致"],
      "meta": {"unit": "u7"}
    },

    {
      "id": "g5lp2p_u8_geom_001",
      "kind": "u8_area_perimeter",
      "topic": "小五生活應用題｜第二包 基礎入門｜帝國",
      "difficulty": "easy",
      "question": "長方形長 8 公分、寬 5 公分，面積是多少平方公分？",
      "answer": "40",
      "answer_mode": "number",
      "hints": ["先判斷是面積。", "長方形面積=長×寬。", "列式 8×5。"],
      "steps": ["公式", "8×5", "得 40"],
      "explanation": "面積 40 平方公分。",
      "common_mistakes": ["用周長公式", "平方單位漏寫"],
      "tags": ["生活應用", "面積"],
      "core": ["長方形面積"],
      "meta": {"unit": "u8"}
    },
    {
      "id": "g5lp2p_u8_geom_002",
      "kind": "u8_area_perimeter",
      "topic": "小五生活應用題｜第二包 基礎入門｜帝國",
      "difficulty": "easy",
      "question": "長方形長 7 公分、寬 4 公分，周長是多少公分？",
      "answer": "22",
      "answer_mode": "number",
      "hints": ["先判斷是周長。", "周長=2×(長+寬)。", "列式 2×(7+4)。"],
      "steps": ["7+4=11", "2×11", "得 22"],
      "explanation": "周長 22 公分。",
      "common_mistakes": ["周長算成面積", "只算一邊"],
      "tags": ["生活應用", "周長"],
      "core": ["長方形周長"],
      "meta": {"unit": "u8"}
    },
    {
      "id": "g5lp2p_u8_geom_003",
      "kind": "u8_area_perimeter",
      "topic": "小五生活應用題｜第二包 基礎入門｜帝國",
      "difficulty": "medium",
      "question": "複合圖形可拆成 6×4 與 2×3 兩個長方形，總面積是多少？",
      "answer": "30",
      "answer_mode": "number",
      "hints": ["先拆圖再分別算面積。", "列式：(6×4)+(2×3)。", "最後加總。"],
      "steps": ["6×4=24", "2×3=6", "24+6=30"],
      "explanation": "總面積 30。",
      "common_mistakes": ["漏算其中一塊", "先加邊長再乘"],
      "tags": ["生活應用", "複合圖形"],
      "core": ["割補"],
      "meta": {"unit": "u8"}
    },
    {
      "id": "g5lp2p_u8_geom_004",
      "kind": "u8_area_perimeter",
      "topic": "小五生活應用題｜第二包 基礎入門｜帝國",
      "difficulty": "medium",
      "question": "三角形底 10 公分、高 6 公分，面積多少平方公分？",
      "answer": "30",
      "answer_mode": "number",
      "hints": ["三角形面積是底×高÷2。", "列式 10×6÷2。", "注意先乘後除。"],
      "steps": ["10×6=60", "60÷2", "得 30"],
      "explanation": "面積 30 平方公分。",
      "common_mistakes": ["忘記除以 2", "底與高辨識錯"],
      "tags": ["生活應用", "三角形面積"],
      "core": ["面積公式"],
      "meta": {"unit": "u8"}
    },
    {
      "id": "g5lp2p_u8_geom_005",
      "kind": "u8_area_perimeter",
      "topic": "小五生活應用題｜第二包 基礎入門｜帝國",
      "difficulty": "hard",
      "question": "正方形邊長 9 公分，面積是多少平方公分？",
      "answer": "81",
      "answer_mode": "number",
      "hints": ["正方形面積=邊長×邊長。", "列式 9×9。", "確認單位為平方公分。"],
      "steps": ["公式", "9×9", "得 81"],
      "explanation": "面積 81 平方公分。",
      "common_mistakes": ["算成周長 36", "平方單位漏寫"],
      "tags": ["生活應用", "正方形面積"],
      "core": ["平方概念"],
      "meta": {"unit": "u8"}
    },

    {
      "id": "g5lp2p_u9_time_001",
      "kind": "u9_time_trip",
      "topic": "小五生活應用題｜第二包 基礎入門｜帝國",
      "difficulty": "easy",
      "question": "2:35 再過 50 分鐘是幾點幾分？",
      "answer": "3:25",
      "answer_mode": "time",
      "hints": ["時間加法注意 60 進位。", "先把分鐘相加。", "超過 60 分就進 1 小時。"],
      "steps": ["35+50=85 分", "85 分=1 小時 25 分", "2:35 變 3:25"],
      "explanation": "2:35 + 50 分 = 3:25。",
      "common_mistakes": ["分鐘不進位", "小時沒加 1"],
      "tags": ["生活應用", "時間加法"],
      "core": ["60進位"],
      "meta": {"unit": "u9"}
    },
    {
      "id": "g5lp2p_u9_time_002",
      "kind": "u9_time_trip",
      "topic": "小五生活應用題｜第二包 基礎入門｜帝國",
      "difficulty": "easy",
      "question": "4:10 往前 1 小時 45 分鐘是幾點幾分？",
      "answer": "2:25",
      "answer_mode": "time",
      "hints": ["這是時間減法。", "先減 1 小時再減 45 分。", "分鐘不足要借位。"],
      "steps": ["4:10-1:00=3:10", "3:10-0:45", "借位得 2:25"],
      "explanation": "4:10 - 1:45 = 2:25。",
      "common_mistakes": ["分鐘不借位", "先後順序錯"],
      "tags": ["生活應用", "時間減法"],
      "core": ["借位"],
      "meta": {"unit": "u9"}
    },
    {
      "id": "g5lp2p_u9_time_003",
      "kind": "u9_time_trip",
      "topic": "小五生活應用題｜第二包 基礎入門｜帝國",
      "difficulty": "medium",
      "question": "8:20 出發，車程 1 小時 35 分，幾點到？",
      "answer": "9:55",
      "answer_mode": "time",
      "hints": ["時間點 + 行程時間。", "先加 1 小時，再加 35 分。", "檢查分鐘是否進位。"],
      "steps": ["8:20+1:00=9:20", "9:20+0:35", "得 9:55"],
      "explanation": "到達時間 9:55。",
      "common_mistakes": ["把 35 分當 0.35 小時直接加", "分鐘進位錯"],
      "tags": ["生活應用", "行程時間"],
      "core": ["時間軸"],
      "meta": {"unit": "u9"}
    },
    {
      "id": "g5lp2p_u9_time_004",
      "kind": "u9_time_trip",
      "topic": "小五生活應用題｜第二包 基礎入門｜帝國",
      "difficulty": "medium",
      "question": "電影從 13:40 到 15:25，共播了多久？",
      "answer": "1:45",
      "answer_mode": "time",
      "hints": ["結束 - 開始。", "先從 13:40 到 14:40。", "再加到 15:25。"],
      "steps": ["13:40→14:40=1:00", "14:40→15:25=0:45", "共 1:45"],
      "explanation": "共 1 小時 45 分。",
      "common_mistakes": ["直接做數字減法", "分鐘借位錯"],
      "tags": ["生活應用", "經過時間"],
      "core": ["時間差"],
      "meta": {"unit": "u9"}
    },
    {
      "id": "g5lp2p_u9_time_005",
      "kind": "u9_time_trip",
      "topic": "小五生活應用題｜第二包 基礎入門｜帝國",
      "difficulty": "hard",
      "question": "23:30 再過 90 分鐘是幾點幾分？",
      "answer": "1:00",
      "answer_mode": "time",
      "hints": ["先把 90 分拆成 60+30。", "23:30+60 分先跨到下一天。", "再加 30 分。"],
      "steps": ["23:30+1:00=0:30", "0:30+0:30", "得 1:00"],
      "explanation": "結果是次日 1:00。",
      "common_mistakes": ["跨日後小時不歸零", "90 分當 0.9 小時"],
      "tags": ["生活應用", "跨日時間"],
      "core": ["24小時制"],
      "meta": {"unit": "u9"}
    },

    {
      "id": "g5lp2p_u10_mix_001",
      "kind": "u10_multi_step",
      "topic": "小五生活應用題｜第二包 基礎入門｜帝國",
      "difficulty": "medium",
      "question": "買 3 本筆記本每本 25 元、2 支筆每支 18 元，付 120 元，找回多少元？",
      "answer": "9",
      "answer_mode": "number",
      "hints": ["先分項算總價。", "筆記本和筆分別算後再相加。", "找零=付款-總價。"],
      "steps": ["25×3=75", "18×2=36，總價111", "120-111=9"],
      "explanation": "找回 9 元。",
      "common_mistakes": ["漏算其中一項", "加減順序錯"],
      "tags": ["生活應用", "多步驟"],
      "core": ["分段列式"],
      "meta": {"unit": "u10"}
    },
    {
      "id": "g5lp2p_u10_mix_002",
      "kind": "u10_multi_step",
      "topic": "小五生活應用題｜第二包 基礎入門｜帝國",
      "difficulty": "hard",
      "question": "全班 36 人，3/4 參加校外教學，每人票價 120 元，總票價多少元？",
      "answer": "3240",
      "answer_mode": "number",
      "hints": ["先求參加人數。", "參加人數=36×3/4。", "再乘每人票價。"],
      "steps": ["36×3/4=27", "27×120", "得 3240"],
      "explanation": "總票價 3240 元。",
      "common_mistakes": ["把 3/4 和 120 先乘", "人數未取整檢查"],
      "tags": ["生活應用", "分率", "金額"],
      "core": ["部分求量", "乘法"],
      "meta": {"unit": "u10"}
    },
    {
      "id": "g5lp2p_u10_mix_003",
      "kind": "u10_multi_step",
      "topic": "小五生活應用題｜第二包 基礎入門｜帝國",
      "difficulty": "hard",
      "question": "食譜 5 人份用 750 公克米，若做 8 人份需多少公克米？",
      "answer": "1200",
      "answer_mode": "number",
      "hints": ["先求每人份。", "每人份=750÷5。", "再乘 8。"],
      "steps": ["750÷5=150", "150×8", "得 1200"],
      "explanation": "需 1200 公克。",
      "common_mistakes": ["直接 750×8", "比例未先單位化"],
      "tags": ["生活應用", "比例配方"],
      "core": ["單位率"],
      "meta": {"unit": "u10"}
    },
    {
      "id": "g5lp2p_u10_mix_004",
      "kind": "u10_multi_step",
      "topic": "小五生活應用題｜第二包 基礎入門｜帝國",
      "difficulty": "medium",
      "question": "跑步速率 6 公里/小時，跑了 45 分鐘，共跑幾公里？",
      "answer": "4.5",
      "answer_mode": "number",
      "hints": ["先統一時間單位為小時。", "45 分鐘=0.75 小時。", "路程=速率×時間。"],
      "steps": ["45分=0.75小時", "6×0.75", "得 4.5 公里"],
      "explanation": "共跑 4.5 公里。",
      "common_mistakes": ["45 直接乘 6", "分鐘未換小時"],
      "tags": ["生活應用", "速率"],
      "core": ["單位一致"],
      "meta": {"unit": "u10"}
    },
    {
      "id": "g5lp2p_u10_mix_005",
      "kind": "u10_multi_step",
      "topic": "小五生活應用題｜第二包 基礎入門｜帝國",
      "difficulty": "medium",
      "question": "長方形花圃長 12 公尺、寬 9 公尺，若保留 18 平方公尺做步道，實際種植面積多少平方公尺？",
      "answer": "90",
      "answer_mode": "number",
      "hints": ["先求花圃總面積。", "總面積=長×寬。", "再扣掉步道面積。"],
      "steps": ["12×9=108", "108-18", "得 90"],
      "explanation": "實際種植面積 90 平方公尺。",
      "common_mistakes": ["先減邊長再乘", "面積單位錯"],
      "tags": ["生活應用", "面積", "多步驟"],
      "core": ["先乘後減"],
      "meta": {"unit": "u10"}
    }
  ]
}
